{
    "$schema": "/redfish/v1/Schemas/redfish-schema.v1_2_0.json",
    "title": "#ManagerAccount.ManagerAccount",
    "$ref": "#/definitions/ManagerAccount",
    "definitions": {
        "ManagerAccount": {
            "anyOf": [
                {
                    "$ref": "/redfish/v1/Schemas/odata.4.0.0.json#/definitions/idRef"
                },
                {
                    "$ref": "/redfish/v1/Schemas/ManagerAccount.v1_0_0.json#/definitions/ManagerAccount"
                },
                {
                    "$ref": "/redfish/v1/Schemas/ManagerAccount.v1_0_2.json#/definitions/ManagerAccount"
                },
                {
                    "$ref": "/redfish/v1/Schemas/ManagerAccount.v1_0_3.json#/definitions/ManagerAccount"
                },
                {
                    "$ref": "/redfish/v1/Schemas/ManagerAccount.v1_0_4.json#/definitions/ManagerAccount"
                },
                {
                    "$ref": "/redfish/v1/Schemas/ManagerAccount.v1_1_0.json#/definitions/ManagerAccount"
                }
            ]
        }
    },
    "copyright": "Copyright 2014-2017 Distributed Management Task Force, Inc. (DMTF). For the full DMTF copyright policy, see http://www.dmtf.org/about/policies/copyright"
}
